old_files/uart/uart_to_bram_ctrl.v
`timescale 1ns / 1ps
// uart_to_bram_ctrl.v - Sequential Loader for Image Data
// Author: Abhirup Paul

module uart_to_bram_ctrl (
    input  wire        clk,          // 100 MHz System Clock
    input  wire        reset_n,      // Active-low reset

    // Interface from your uart_rx.v
    input  wire        rx_done,      // Pulse when 8-bit data is ready
    input  wire [7:0]  rx_data,      // The received pixel byte

    // Interface to Soumik's img_bram_in
    output reg [13:0]  write_addr,   // 14-bit addr for 128x128 image
    output reg [7:0]   write_data,   // Data to BRAM
    output reg         we,           // Write Enable pulse

    // Status to Top Level
    output reg         image_loaded  // High when 16,384 bytes are stored
);

    // Constant for 128x128 image size [cite: 229]
    localparam MAX_PIXELS = 16384;

    always @(posedge clk or negedge reset_n) begin
        if (!reset_n) begin
            write_addr   <= 14'd0;
            write_data   <= 8'd0;
            we           <= 1'b0;
            image_loaded <= 1'b0;
        end else begin
            // Default: Pull Write Enable low after 1 cycle
            we <= 1'b0;

            if (rx_done && !image_loaded) begin
                // 1. Prepare data and address
                write_data <= rx_data;
                we         <= 1'b1; // Trigger BRAM write

                // 2. Increment address or finish loading
                if (write_addr < MAX_PIXELS - 1) begin
                    write_addr <= write_addr + 14'd1;
                end else begin
                    image_loaded <= 1'b1; // All 16,384 pixels received
                end
            end
        end
    end

endmodule

old_files/uart/uart_tx.v
// uart_tx.v  — Fixed version
// Bugs fixed:
//   [FIX-TX-1] CRITICAL: count and index were never reset inside the IDLE
//               state.  After the first transmission both registers held their
//               end-of-frame values (count = CLKS_PER_BIT-1, index = 7).
//               On the very next START state the "count < CLKS_PER_BIT-1"
//               guard was already false, so the start bit was skipped in 0
//               clock cycles and DATA began immediately — producing a
//               malformed frame from the second byte onward.
//               Fix: reset count and index in the IDLE state.
//   [FIX-TX-2] Added synchronous reset (rst) for synthesis safety.

module uart_tx #(parameter CLKS_PER_BIT = 87) (
    input            clk,
    input            rst,       // synchronous active-high reset
    input            tx_start,  // assert for one cycle to begin transmission
    input      [7:0] tx_byte,   // byte to transmit (must be stable while busy)
    output reg       tx_serial, // UART TX line
    output reg       tx_done    // 1-cycle pulse when frame is complete
);
    localparam IDLE  = 3'b000,
               START = 3'b001,
               DATA  = 3'b010,
               STOP  = 3'b011;

    reg [2:0] state = IDLE;
    reg [7:0] count = 0;
    reg [2:0] index = 0;

    always @(posedge clk) begin
        if (rst) begin
            state     <= IDLE;
            tx_serial <= 1'b1;
            tx_done   <= 1'b0;
            count     <= 0;
            index     <= 0;
        end else begin
            case (state)
                // --------------------------------------------------------
                IDLE: begin
                    tx_serial <= 1'b1;   // line idles high
                    tx_done   <= 1'b0;
                    // [FIX-TX-1] Always reset count and index in IDLE so
                    // subsequent transmissions begin cleanly.
                    count     <= 0;
                    index     <= 0;
                    if (tx_start)
                        state <= START;
                end

                // --------------------------------------------------------
                START: begin
                    tx_serial <= 1'b0;   // pull line low for start bit
                    if (count < CLKS_PER_BIT - 1)
                        count <= count + 1;
                    else begin
                        count <= 0;
                        state <= DATA;
                    end
                end

                // --------------------------------------------------------
                DATA: begin
                    tx_serial <= tx_byte[index];
                    if (count < CLKS_PER_BIT - 1) begin
                        count <= count + 1;
                    end else begin
                        count <= 0;
                        if (index < 7)
                            index <= index + 1;
                        else
                            state <= STOP;
                    end
                end

                // --------------------------------------------------------
                STOP: begin
                    tx_serial <= 1'b1;   // stop bit — line high
                    if (count < CLKS_PER_BIT - 1) begin
                        count <= count + 1;
                    end else begin
                        tx_done <= 1'b1;
                        state   <= IDLE;
                    end
                end

                default: begin
                    tx_serial <= 1'b1;
                    state     <= IDLE;
                end
            endcase
        end
    end
endmodule

uart/uart_rx.v
// uart_rx.v  — Fixed version
// Bugs fixed:
//   [FIX-RX-1] START state now validates the start bit is still LOW at the
//               mid-point sample.  A glitch shorter than half a bit period no
//               longer causes a false reception.
//   [FIX-RX-2] STOP state now validates the stop bit is HIGH before asserting
//               rx_dv.  A framing error (missing stop bit) is silently
//               discarded and the FSM returns to IDLE to re-sync.
//   [FIX-RX-3] count is explicitly reset in STOP→IDLE transition so there is
//               no stale counter value on the next reception.
//   [FIX-RX-4] Added synchronous reset input (rst) so the module is safely
//               usable in synthesis (inline initialisation only works in sim).

module uart_rx #(parameter CLKS_PER_BIT = 87) (
    input            clk,
    input            rst,        // synchronous active-high reset
    input            rx_serial,  // physical RX pin
    output reg       rx_dv,      // 1-cycle data-valid pulse
    output reg [7:0] rx_byte     // received byte (stable when rx_dv is high)
);
    localparam IDLE  = 3'b000,
               START = 3'b001,
               DATA  = 3'b010,
               STOP  = 3'b011;

    reg [2:0] state = IDLE;
    reg [7:0] count = 0;   // 8 bits is enough for CLKS_PER_BIT up to 255
    reg [2:0] index = 0;

    always @(posedge clk) begin
        if (rst) begin
            state   <= IDLE;
            count   <= 0;
            index   <= 0;
            rx_dv   <= 0;
            rx_byte <= 0;
        end else begin
            case (state)
                // --------------------------------------------------------
                IDLE: begin
                    rx_dv <= 0;
                    count <= 0;
                    index <= 0;
                    // Falling edge on rx_serial → possible start bit
                    if (rx_serial == 1'b0)
                        state <= START;
                end

                // --------------------------------------------------------
                // Wait until the middle of the start bit, then verify it
                // is still LOW.  If it has gone high it was just a glitch.
                START: begin
                    if (count < (CLKS_PER_BIT - 1) / 2) begin
                        count <= count + 1;
                    end else begin
                        count <= 0;
                        // [FIX-RX-1] Validate start bit at mid-point
                        if (rx_serial == 1'b0)
                            state <= DATA;
                        else
                            state <= IDLE;   // glitch – abort
                    end
                end

                // --------------------------------------------------------
                DATA: begin
                    if (count < CLKS_PER_BIT - 1) begin
                        count <= count + 1;
                    end else begin
                        count           <= 0;
                        rx_byte[index]  <= rx_serial;
                        if (index < 7)
                            index <= index + 1;
                        else
                            state <= STOP;
                    end
                end

                // --------------------------------------------------------
                // Wait a full bit period, then sample the stop bit.
                STOP: begin
                    if (count < CLKS_PER_BIT - 1) begin
                        count <= count + 1;
                    end else begin
                        count <= 0;           // [FIX-RX-3] reset count
                        // [FIX-RX-2] Validate stop bit is HIGH
                        if (rx_serial == 1'b1)
                            rx_dv <= 1;       // valid frame
                        // framing error: rx_dv stays 0, byte discarded
                        state <= IDLE;
                    end
                end

                default: state <= IDLE;
            endcase
        end
    end
endmodule

old_files/uart/top_uart.v
`timescale 1ns/1ps

module top_uart #(parameter CLKS_PER_BIT = 87) (
    input  wire        clk,
    input  wire        rst,       // Active-high reset from testbench/system
    input  wire        rx_pin,    // Serial RX input from PC
    output wire        tx_pin,    // Serial TX output to PC
    
    // TX Control (for CPU interaction or loopback testing)
    input  wire [7:0]  tx_data,
    input  wire        tx_en,
    output wire        tx_busy,   
    
    // RX Data Output
    output wire [7:0]  rx_data,
    output wire        rx_ready,
    
    // BRAM Controller Interface (Image Loader)
    output wire [13:0] bram_write_addr,
    output wire [7:0]  bram_write_data,
    output wire        bram_we,
    output wire        image_loaded
);

    // Internal wires
    wire tx_done_w;

    // ---------------------------------------------------------------------
    // 1. UART Receiver
    // ---------------------------------------------------------------------
    uart_rx #(.CLKS_PER_BIT(CLKS_PER_BIT)) u_rx (
        .clk       (clk),
        .rst       (rst),         // Active-high
        .rx_serial (rx_pin),
        .rx_dv     (rx_ready),
        .rx_byte   (rx_data)
    );

    // ---------------------------------------------------------------------
    // 2. UART Transmitter
    // ---------------------------------------------------------------------
    uart_tx #(.CLKS_PER_BIT(CLKS_PER_BIT)) u_tx (
        .clk       (clk),
        .rst       (rst),         // Active-high
        .tx_start  (tx_en),
        .tx_byte   (tx_data),
        .tx_serial (tx_pin),
        .tx_done   (tx_done_w)
    );

    // ---------------------------------------------------------------------
    // 3. TX Busy Status Latch
    // ---------------------------------------------------------------------
    // Set 'busy' high when tx_en is triggered, clear it when tx_done pulses.
    reg busy_reg;
    always @(posedge clk) begin
        if (rst) begin
            busy_reg <= 1'b0;
        end else if (tx_en) begin
            busy_reg <= 1'b1;
        end else if (tx_done_w) begin
            busy_reg <= 1'b0;
        end
    end
    assign tx_busy = busy_reg;

    // ---------------------------------------------------------------------
    // 4. UART to BRAM Controller (Image Loader)
    // ---------------------------------------------------------------------
    // Notice the ~rst: We invert the active-high rst to drive the active-low reset_n
    uart_to_bram_ctrl u_bram_ctrl (
        .clk          (clk),
        .reset_n      (~rst),     
        .rx_done      (rx_ready),
        .rx_data      (rx_data),
        .write_addr   (bram_write_addr),
        .write_data   (bram_write_data),
        .we           (bram_we),
        .image_loaded (image_loaded)
    );

endmodule

uart/tb_uart.v
// tb_uart.v  — Fixed testbench
// Bugs fixed:
//   [FIX-TB-1] uart_controller instantiation was missing tx_data and tx_en
//               ports.  Those inputs were floating (Z / X), which caused
//               X-propagation through the TX datapath.
//   [FIX-TB-2] The pass/fail check sampled rx_ready (rx_dv) after a 2000 ns
//               delay.  rx_dv is a single-cycle pulse (~10 ns wide); it had
//               long since de-asserted by the time the check ran, so the
//               test *always* reported FAIL.
//               Fix: latch rx_data when rx_ready pulses, then compare the
//               latched value.
//   [FIX-TB-3] rst was not driven.  Added a short reset at the start so all
//               FSMs initialise to a known state (required for synthesis-
//               equivalent simulation behaviour).
//   [FIX-TB-4] tx_data and tx_en are now tied to a safe idle value (0 / 0)
//               to avoid X-propagation during the RX-only test.











// `timescale 1ns/1ps

// module tb_uart();

//     // -----------------------------------------------------------------------
//     // DUT signals
//     // -----------------------------------------------------------------------
//     reg        clk   = 1'b0;
//     reg        rst   = 1'b1;   // start in reset
//     reg        rx_pin = 1'b1;

//     // TX side — tied off for this RX-only test [FIX-TB-4]
//     reg  [7:0] tx_data = 8'h00;
//     reg        tx_en   = 1'b0;

//     wire       tx_pin;
//     wire [7:0] rx_data;
//     wire       rx_ready;

//     // [FIX-TB-2] Latch the received byte on the rx_ready pulse
//     reg  [7:0] rx_data_latched = 8'hFF;
//     reg        rx_received     = 1'b0;

//     always @(posedge clk) begin
//         if (rx_ready) begin
//             rx_data_latched <= rx_data;
//             rx_received     <= 1'b1;
//         end
//     end

//     // -----------------------------------------------------------------------
//     // 100 MHz clock  (period = 10 ns)
//     // -----------------------------------------------------------------------
//     always #5 clk = ~clk;

//     // -----------------------------------------------------------------------
//     // DUT instantiation
//     // -----------------------------------------------------------------------
//     top_uart dut (
//         .clk     (clk),
//         .rst     (rst),
//         .rx_pin  (rx_pin),
//         .tx_pin  (tx_pin),
//         .tx_data (tx_data),   // [FIX-TB-1] connected
//         .tx_en   (tx_en),     // [FIX-TB-1] connected
//         .rx_data (rx_data),
//         .rx_ready(rx_ready),
//         .tx_busy ()
//     );

//     // -----------------------------------------------------------------------
//     // Stimulus — transmit 0x41 ('A') LSB first
//     //
//     // CLKS_PER_BIT = 87  →  bit period = 87 × 10 ns = 870 ns
//     //
//     // 0x41 = 0100_0001
//     // LSB-first bit order: 1 0 0 0 0 0 1 0
//     // -----------------------------------------------------------------------
//     initial begin
//         $dumpfile("uart_test.vcd");
//         $dumpvars(0, tb_uart);

//         // [FIX-TB-3] Hold reset for a few cycles then release
//         repeat (4) @(posedge clk);
//         rst = 1'b0;

//         // Allow the FSMs to settle in IDLE
//         #100;

//         // --- UART frame for 0x41 ---
//         rx_pin = 1'b0; #870;   // Start bit  (LOW)
//         rx_pin = 1'b1; #870;   // Bit 0 = 1
//         rx_pin = 1'b0; #870;   // Bit 1 = 0
//         rx_pin = 1'b0; #870;   // Bit 2 = 0
//         rx_pin = 1'b0; #870;   // Bit 3 = 0
//         rx_pin = 1'b0; #870;   // Bit 4 = 0
//         rx_pin = 1'b0; #870;   // Bit 5 = 0
//         rx_pin = 1'b1; #870;   // Bit 6 = 1
//         rx_pin = 1'b0; #870;   // Bit 7 = 0
//         rx_pin = 1'b1; #870;   // Stop bit  (HIGH)

//         // [FIX-TB-2] Wait for the rx_received latch (set by rx_ready pulse)
//         // Give enough time for the stop-bit processing to complete.
//         wait (rx_received || $time > 20_000);

//         // Extra settling margin
//         #100;

//         // --- Result ---
//         if (rx_received && rx_data_latched == 8'h41)
//             $display("UART PASS: received 0x%02X ('A')", rx_data_latched);
//         else if (!rx_received)
//             $display("UART FAIL: rx_ready pulse never observed");
//         else
//             $display("UART FAIL: expected 0x41, got 0x%02X", rx_data_latched);



//         // --- Result ---
//         if (rx_received && rx_data_latched == 8'h41)
//             $display("UART PASS: received 0x%02X ('A')", rx_data_latched);
//         else if (!rx_received)
//             $display("UART FAIL: rx_ready pulse never observed");
//         else
//             $display("UART FAIL: expected 0x41, got 0x%02X", rx_data_latched);

//         // -----------------------------------------------------------------------
//         // Stimulus — Verify TX by transmitting 0x55 (alternating bits: 01010101)
//         // -----------------------------------------------------------------------
//         $display("Starting TX test...");
//         tx_data = 8'h55; 
//         tx_en   = 1'b1;  // Pulse enable high
//         #10;             // Wait 1 clock cycle
//         tx_en   = 1'b0;  // Pull enable low

//         // Wait for the transmission to finish (10 bits * 870ns per bit)
//         #10000; 
        
//         $display("TX test complete. Check GTKWave for the tx_pin waveform!");



//         $finish;
//     end

// endmodule


















`timescale 1ns/1ps

module tb_uart();

    // -----------------------------------------------------------------------
    // DUT signals & Constants
    // -----------------------------------------------------------------------
    parameter BIT_PERIOD = 870; // 87 clocks * 10ns = 870ns per bit

    reg        clk   = 1'b0;
    reg        rst   = 1'b1;
    reg        rx_pin = 1'b1;
    
    reg  [7:0] tx_data = 8'h00;
    reg        tx_en   = 1'b0;
    wire       tx_pin;
    
    wire [7:0] rx_data;
    wire       rx_ready;
    wire       tx_busy;

    // Latch for RX checking
    reg  [7:0] rx_latched;
    reg        rx_flag = 1'b0;

    always @(posedge clk) begin
        if (rx_ready) begin
            rx_latched <= rx_data;
            rx_flag    <= 1'b1;
        end
    end

    // 100 MHz clock
    always #5 clk = ~clk;

    // -----------------------------------------------------------------------
    // DUT instantiation
    // -----------------------------------------------------------------------
    top_uart dut (
        .clk     (clk),
        .rst     (rst),
        .rx_pin  (rx_pin),
        .tx_pin  (tx_pin),
        .tx_data (tx_data),
        .tx_en   (tx_en),
        .rx_data (rx_data),
        .rx_ready(rx_ready),
        .tx_busy (tx_busy)
    );

    // -----------------------------------------------------------------------
    // VERILOG TASKS (Automated Test Functions)
    // -----------------------------------------------------------------------
    
    // Task 1: Send a byte to the FPGA perfectly
    task send_rx_byte;
        input [7:0] data;
        integer i;
        begin
            rx_pin = 1'b0; #BIT_PERIOD; // Start Bit
            for (i=0; i<8; i=i+1) begin
                rx_pin = data[i]; #BIT_PERIOD; // Data Bits (LSB first)
            end
            rx_pin = 1'b1; #BIT_PERIOD; // Stop Bit
        end
    endtask

    // Task 2: Command the FPGA to transmit
    task trigger_tx;
        input [7:0] data;
        begin
            tx_data = data;
            tx_en   = 1'b1;
            #10;
            tx_en   = 1'b0;
            wait(!tx_busy); // Wait until the hardware finishes sending
        end
    endtask

    // -----------------------------------------------------------------------
    // THE STRESS TEST SUITE
    // -----------------------------------------------------------------------
    initial begin
        $dumpfile("uart_stress_test.vcd");
        $dumpvars(0, tb_uart);

        $display("==================================================");
        $display("          UART EXTREME STRESS TEST SUITE          ");
        $display("==================================================");

        // Reset Sequence
        repeat (4) @(posedge clk);
        rst = 1'b0;
        #100;

        // ---------------------------------------------------------
        $display("\n--- TEST 1: GLITCH REJECTION ---");
        // Drop the line LOW for only 200ns (less than half a bit), then back HIGH.
        // If the RX module is robust, it should ignore this and NOT fire rx_ready.
        rx_flag = 0;
        rx_pin = 1'b0; #200; 
        rx_pin = 1'b1; #1000;
        if (rx_flag == 1) $display("[FAIL] Glitch triggered a fake reception!");
        else              $display("[PASS] Glitch successfully ignored.");

        // ---------------------------------------------------------
        $display("\n--- TEST 2: FULL-DUPLEX COLLISION ---");
        // We use 'fork...join' to run RX and TX at the exact same time.
        // This proves the two state machines do not interfere with each other.
        rx_flag = 0;
        fork
            send_rx_byte(8'hAA);      // PC sends 10101010 to FPGA
            trigger_tx(8'h55);        // FPGA sends 01010101 to PC
        join
        
        #100; // Settle
        if (rx_latched == 8'hAA) $display("[PASS] Full-Duplex successful! RX = 0xAA, TX = 0x55");
        else                     $display("[FAIL] Full-Duplex corrupted RX data: %h", rx_latched);

        // ---------------------------------------------------------
        $display("\n--- TEST 3: BACK-TO-BACK BURST (IMAGE STREAM SIMULATION) ---");
        // Send 3 bytes with ZERO delay between the stop bit and the next start bit.
        // This is exactly how the Python script will stream the image.
        rx_flag = 0;
        
        send_rx_byte(8'h11);
        if (rx_latched == 8'h11) $display("[PASS] Burst Byte 1: 0x11"); else $display("[FAIL] Burst 1");
        
        send_rx_byte(8'h22);
        if (rx_latched == 8'h22) $display("[PASS] Burst Byte 2: 0x22"); else $display("[FAIL] Burst 2");
        
        send_rx_byte(8'h33);
        if (rx_latched == 8'h33) $display("[PASS] Burst Byte 3: 0x33"); else $display("[FAIL] Burst 3");

        $display("\n==================================================");
        $display("               TEST SUITE COMPLETE                ");
        $display("==================================================");
        
        #500;
        $finish;
    end

endmodule

uart/uart_stress_test.vcd
$date
   Fri Apr 10 16:48:09 2026
$end

$version
  2025.2
  $dumpfile ("uart_stress_test.vcd") 
$end

$timescale
  1ps
$end

$scope module tb_uart $end
$var reg 1 ! clk $end
$var reg 1 " rst $end
$var reg 1 # rx_pin $end
$var reg 8 $ tx_data [7:0] $end
$var reg 1 % tx_en $end
$var wire 1 & tx_pin $end
$var wire 8 ' rx_data [7:0] $end
$var wire 1 ( rx_ready $end
$var wire 1 ) tx_busy $end
$var reg 8 * rx_latched [7:0] $end
$var reg 1 + rx_flag $end
$scope module dut $end
$var wire 1 , clk $end
$var wire 1 - rst $end
$var wire 1 . rx_pin $end
$var wire 1 & tx_pin $end
$var wire 8 / tx_data [7:0] $end
$var wire 1 0 tx_en $end
$var wire 1 ) tx_busy $end
$var wire 8 ' rx_data [7:0] $end
$var wire 1 ( rx_ready $end
$var wire 14 1 bram_write_addr [13:0] $end
$var wire 8 2 bram_write_data [7:0] $end
$var wire 1 3 bram_we $end
$var wire 1 4 image_loaded $end
$var wire 1 5 tx_done_w $end
$var reg 1 6 busy_reg $end
$scope module u_rx $end
$var wire 1 , clk $end
$var wire 1 - rst $end
$var wire 1 . rx_serial $end
$var reg 1 7 rx_dv $end
$var reg 8 8 rx_byte [7:0] $end
$var reg 3 9 state [2:0] $end
$var reg 8 : count [7:0] $end
$var reg 3 ; index [2:0] $end
$upscope $end
$scope module u_tx $end
$var wire 1 , clk $end
$var wire 1 - rst $end
$var wire 1 0 tx_start $end
$var wire 8 / tx_byte [7:0] $end
$var reg 1 < tx_serial $end
$var reg 1 = tx_done $end
$var reg 3 > state [2:0] $end
$var reg 8 ? count [7:0] $end
$var reg 3 @ index [2:0] $end
$upscope $end
$scope module u_bram_ctrl $end
$var wire 1 , clk $end
$var wire 1 A reset_n $end
$var wire 1 ( rx_done $end
$var wire 8 ' rx_data [7:0] $end
$var reg 14 B write_addr [13:0] $end
$var reg 8 C write_data [7:0] $end
$var reg 1 D we $end
$var reg 1 E image_loaded $end
$upscope $end
$upscope $end
$scope task send_rx_byte $end
$var reg 8 F data [7:0] $end
$var integer 32 G i [31:0] $end
$upscope $end
$scope task trigger_tx $end
$var reg 8 H data [7:0] $end
$upscope $end
$upscope $end
$enddefinitions $end

#0
$dumpvars
0!
1"
1#
b0 $
0%
x&
bx '
x(
x)
bx *
0+
0,
1-
1.
b0 /
00
b0 1
b0 2
03
04
x5
x6
x7
bx 8
b0 9
b0 :
b0 ;
x<
x=
b0 >
b0 ?
b0 @
0A
b0 B
b0 C
0D
0E
bx F
bx G
bx H
$end

#5000
1!
1&
b0 '
0(
0)
1,
05
06
07
b0 8
1<
0=

#10000
0!
0,

#15000
1!
1,

#20000
0!
0,

#25000
1!
1,

#30000
0!
0,

#35000
1!
0"
1,
0-
1A

#40000
0!
0,

#45000
1!
1,

#50000
0!
0,

#55000
1!
1,

#60000
0!
0,

#65000
1!
1,

#70000
0!
0,

#75000
1!
1,

#80000
0!
0,

#85000
1!
1,

#90000
0!
0,

#95000
1!
1,

#100000
0!
0,

#105000
1!
1,

#110000
0!
0,

#115000
1!
1,

#120000
0!
0,

#125000
1!
1,

#130000
0!
0,

#135000
1!
0#
1,
0.
b1 9

#140000
0!
0,

#145000
1!
1,
b1 :

#150000
0!
0,

#155000
1!
1,
b10 :

#160000
0!
0,

#165000
1!
1,
b11 :

#170000
0!
0,

#175000
1!
1,
b100 :

#180000
0!
0,

#185000
1!
1,
b101 :

#190000
0!
0,

#195000
1!
1,
b110 :

#200000
0!
0,

#205000
1!
1,
b111 :

#210000
0!
0,

#215000
1!
1,
b1000 :

#220000
0!
0,

#225000
1!
1,
b1001 :

#230000
0!
0,

#235000
1!
1,
b1010 :

#240000
0!
0,

#245000
1!
1,
b1011 :

#250000
0!
0,

#255000
1!
1,
b1100 :

#260000
0!
0,

#265000
1!
1,
b1101 :

#270000
0!
0,

#275000
1!
1,
b1110 :

#280000
0!
0,

#285000
1!
1,
b1111 :

#290000
0!
0,

#295000
1!
1,
b10000 :

#300000
0!
0,

#305000
1!
1,
b10001 :

#310000
0!
0,

#315000
1!
1,
b10010 :

#320000
0!
0,

#325000
1!
1,
b10011 :

#330000
0!
0,

#335000
1!
1#
1,
1.
b10100 :

#340000
0!
0,

#345000
1!
1,
b10101 :

#350000
0!
0,

#355000
1!
1,
b10110 :

#360000
0!
0,

#365000
1!
1,
b10111 :

#370000
0!
0,

#375000
1!
1,
b11000 :

#380000
0!
0,

#385000
1!
1,
b11001 :

#390000
0!
0,

#395000
1!
1,
b11010 :

#400000
0!
0,

#405000
1!
1,
b11011 :

#410000
0!
0,

#415000
1!
1,
b11100 :

#420000
0!
0,

#425000
1!
1,
b11101 :

#430000
0!
0,

#435000
1!
1,
b11110 :

#440000
0!
0,

#445000
1!
1,
b11111 :

#450000
0!
0,

#455000
1!
1,
b100000 :

#460000
0!
0,

#465000
1!
1,
b100001 :

#470000
0!
0,

#475000
1!
1,
b100010 :

#480000
0!
0,

#485000
1!
1,
b100011 :

#490000
0!
0,

#495000
1!
1,
b100100 :

#500000
0!
0,

#505000
1!
1,
b100101 :

#510000
0!
0,

#515000
1!
1,
b100110 :

#520000
0!
0,

#525000
1!
1,
b100111 :

#530000
0!
0,

#535000
1!
1,
b101000 :

#540000
0!
0,

#545000
1!
1,
b101001 :

#550000
0!
0,

#555000
1!
1,
b101010 :

#560000
0!
0,

#565000
1!
1,
b101011 :

#570000
0!
0,

#575000
1!
1,
b0 9
b0 :

